canyonrun/__init__.py
canyonrun/canyonrun.py
canyonrun/env_utils.py
canyonrun/gym_unity.py
old_canyon/__init__.py
old_canyon/canyonrun03.py
old_canyon/env_utils.py
old_canyon/gym_unity.py
canyonrun-0.0.2.dist-info/METADATA
canyonrun-0.0.2.dist-info/WHEEL
canyonrun-0.0.2.dist-info/top_level.txt
canyonrun-0.0.2.dist-info/RECORD
