Metadata-Version: 2.1
Name: canyonrun
Version: 0.0.2
Summary: Canyon-Run package
Home-page: https://github.com/mlech26l/
Author: Mathias Lechner
Author-email: mlech26l@gmail.com
License: Apache License 2.0
Platform: UNKNOWN
Classifier: Programming Language :: Python
Classifier: Programming Language :: Python :: 3.6
Classifier: Operating System :: Unix
Classifier: Operating System :: Microsoft :: Windows
Classifier: Operating System :: MacOS
Classifier: Intended Audience :: Science/Research
Classifier: Topic :: Scientific/Engineering
Classifier: Topic :: Software Development
Requires-Dist: future
Requires-Dist: packaging
